{
	"credit": "Made with Blockbench",
	"textures": {
		"0": "block/acacia_log",
		"1": "block/black_concrete",
		"particle": "block/acacia_log"
	},
	"elements": [
		{
			"from": [5.44286, 7.08571, 1.52857],
			"to": [6.44286, 10.08571, 14.52857],
			"rotation": {"angle": 0, "axis": "y", "origin": [13.44286, 15.08571, 9.52857]},
			"faces": {
				"north": {"uv": [0, 0, 1, 1], "texture": "#0"},
				"east": {"uv": [0, 0, 1, 1], "texture": "#0"},
				"south": {"uv": [0, 0, 1, 1], "texture": "#0"},
				"west": {"uv": [0, 0, 1, 1], "texture": "#0"},
				"up": {"uv": [0, 0, 1, 1], "texture": "#0"},
				"down": {"uv": [0, 0, 1, 1], "texture": "#0"}
			}
		},
		{
			"from": [7.44286, 7.08571, 1.52857],
			"to": [8.44286, 10.08571, 14.52857],
			"rotation": {"angle": 0, "axis": "y", "origin": [15.44286, 15.08571, 9.52857]},
			"faces": {
				"north": {"uv": [0, 0, 1, 1], "texture": "#0"},
				"east": {"uv": [0, 0, 1, 1], "texture": "#0"},
				"south": {"uv": [0, 0, 1, 1], "texture": "#0"},
				"west": {"uv": [0, 0, 1, 1], "texture": "#0"},
				"up": {"uv": [0, 0, 1, 1], "texture": "#0"},
				"down": {"uv": [0, 0, 1, 1], "texture": "#0"}
			}
		},
		{
			"from": [8.64286, 7.08571, 12.72857],
			"to": [9.64286, 10.08571, 13.72857],
			"rotation": {"angle": 45, "axis": "z", "origin": [9.14286, 8.58571, 13.22857]},
			"faces": {
				"north": {"uv": [0, 0, 1, 1], "texture": "#1"},
				"east": {"uv": [0, 0, 1, 1], "texture": "#1"},
				"south": {"uv": [0, 0, 1, 1], "texture": "#1"},
				"west": {"uv": [0, 0, 1, 1], "texture": "#1"},
				"up": {"uv": [0, 0, 1, 1], "texture": "#1"},
				"down": {"uv": [0, 0, 1, 1], "texture": "#1"}
			}
		},
		{
			"from": [8.64286, 7.08571, 2.52857],
			"to": [9.64286, 10.08571, 3.52857],
			"rotation": {"angle": 45, "axis": "z", "origin": [9.14286, 8.58571, 3.02857]},
			"faces": {
				"north": {"uv": [0, 0, 1, 1], "texture": "#1"},
				"east": {"uv": [0, 0, 1, 1], "texture": "#1"},
				"south": {"uv": [0, 0, 1, 1], "texture": "#1"},
				"west": {"uv": [0, 0, 1, 1], "texture": "#1"},
				"up": {"uv": [0, 0, 1, 1], "texture": "#1"},
				"down": {"uv": [0, 0, 1, 1], "texture": "#1"}
			}
		},
		{
			"from": [8.44286, 7.08571, 1.52857],
			"to": [11.44286, 8.08571, 14.52857],
			"rotation": {"angle": 0, "axis": "y", "origin": [15.44286, 15.08571, 9.52857]},
			"faces": {
				"north": {"uv": [0, 0, 1, 1], "texture": "#0"},
				"east": {"uv": [0, 0, 1, 1], "texture": "#0"},
				"south": {"uv": [0, 0, 1, 1], "texture": "#0"},
				"west": {"uv": [0, 0, 1, 1], "texture": "#0"},
				"up": {"uv": [0, 0, 1, 1], "texture": "#0"},
				"down": {"uv": [0, 0, 1, 1], "texture": "#0"}
			}
		},
		{
			"from": [6.44286, 6.98571, 4.52857],
			"to": [7.44286, 7.08571, 5.12857],
			"rotation": {"angle": 0, "axis": "y", "origin": [12.44286, 14.98571, 12.52857]},
			"faces": {
				"north": {"uv": [0, 0, 1, 1], "texture": "#0"},
				"east": {"uv": [0, 0, 1, 1], "texture": "#0"},
				"south": {"uv": [0, 0, 1, 1], "texture": "#0"},
				"west": {"uv": [0, 0, 1, 1], "texture": "#0"},
				"up": {"uv": [0, 0, 1, 1], "texture": "#0"},
				"down": {"uv": [0, 0, 1, 1], "texture": "#0"}
			}
		},
		{
			"from": [6.44286, 6.98571, 10.52857],
			"to": [7.44286, 7.08571, 11.12857],
			"rotation": {"angle": 0, "axis": "y", "origin": [12.44286, 14.98571, 18.52857]},
			"faces": {
				"north": {"uv": [0, 0, 1, 1], "texture": "#0"},
				"east": {"uv": [0, 0, 1, 1], "texture": "#0"},
				"south": {"uv": [0, 0, 1, 1], "texture": "#0"},
				"west": {"uv": [0, 0, 1, 1], "texture": "#0"},
				"up": {"uv": [0, 0, 1, 1], "texture": "#0"},
				"down": {"uv": [0, 0, 1, 1], "texture": "#0"}
			}
		}
	],
	"display": {
		"head": {
			"translation": [0, 6.75, 0],
			"scale": [2, 2, 2]
		}
	}
}